font_atlas.pyd
font-atlas-stubs/__init__.pyi
font_atlas-1.0.1.dist-info/LICENSE
font_atlas-1.0.1.dist-info/METADATA
font_atlas-1.0.1.dist-info/WHEEL
font_atlas-1.0.1.dist-info/top_level.txt
font_atlas-1.0.1.dist-info/RECORD
